Workbook

Sheet Read Me
A1: StructuralGuard Blind Test Workbook
A3: Scenario | B3: Retail sales detail
A4: Random seed | B4: 11031
A5: Generated rows | B5: 220
A6: Purpose | B6: Blind structural-formula anomaly evaluation
A7: Answer location | B7: Stored outside this workbook
A8: Safety | B8: Do not overwrite this source workbook during analysis

Sheet Parameters
A1: Assumptions
A2: Parameter | B2: Value
A3: Tax rate | B3: 0.13
A4: Discount cap | B4: 0.2
A5: Target margin | B5: 0.35

Sheet Sales Detail
A1: Retail Sales Detail
A2: Order ID | B2: Date | C2: Region | D2: Quantity | E2: Unit Price | F2: Discount | G2: Net Sales | H2: Tax | I2: Gross Sales | J2: Net per Unit
A3: SO-0001 | B3: 46254 | C3: North | D3: 9 | E3: 86.51 | F3: 0 | G3: =ROUND(D3*E3*(1-F3),2) | H3: =ROUND(G3*'Parameters'!$B$3,2) | I3: =G3+H3 | J3: =IF(D3=0,0,ROUND(G3/D3,2))
A4: SO-0002 | B4: 46315 | C4: West | D4: 11 | E4: 148.3 | F4: 0.15 | G4: =ROUND(D4*E4*(1-F4),2) | H4: =ROUND(G4*'Parameters'!$B$3,2) | I4: =G4+H4 | J4: =IF(D4=0,0,ROUND(G4/D4,2))
A5: SO-0003 | B5: 46362 | C5: West | D5: 1 | E5: 188.01 | F5: 0.05 | G5: =ROUND(D5*E5*(1-F5),2) | H5: =ROUND(G5*'Parameters'!$B$3,2) | I5: =G5+H5 | J5: =IF(D5=0,0,ROUND(G5/D5,2))
A6: SO-0004 | B6: 46048 | C6: South | D6: 15 | E6: 11.53 | F6: 0.15 | G6: =ROUND(D6*E6*(1-F6),2) | H6: =ROUND(G6*'Parameters'!$B$3,2) | I6: =G6+H6 | J6: =IF(D6=0,0,ROUND(G6/D6,2))
A7: SO-0005 | B7: 46029 | C7: South | D7: 5 | E7: 81.12 | F7: 0 | G7: =ROUND(D7*E7*(1-F7),2) | H7: =ROUND(G7*'Parameters'!$B$3,2) | I7: =G7+H7 | J7: =IF(D7=0,0,ROUND(G7/D7,2))
A8: SO-0006 | B8: 46352 | C8: North | D8: 6 | E8: 73.71 | F8: 0.1 | G8: =ROUND(D8*E8*(1-F8),2) | H8: =ROUND(G8*'Parameters'!$B$3,2) | I8: =G8+H8 | J8: =IF(D8=0,0,ROUND(G8/D8,2))
A9: SO-0007 | B9: 46375 | C9: North | D9: 2 | E9: 52.11 | F9: 0.15 | G9: =ROUND(D9*E9*(1-F9),2) | H9: =ROUND(G9*'Parameters'!$B$3,2) | I9: =G9+H9 | J9: =IF(D9=0,0,ROUND(G9/D9,2))
A10: SO-0008 | B10: 46097 | C10: South | D10: 15 | E10: 205.92 | F10: 0.15 | G10: =ROUND(D10*E10*(1-F10),2) | H10: =ROUND(G10*'Parameters'!$B$3,2) | I10: =G10+H10 | J10: =IF(D10=0,0,ROUND(G10/D10,2))
A11: SO-0009 | B11: 46373 | C11: North | D11: 2 | E11: 218.91 | F11: 0.05 | G11: =ROUND(D11*E11*(1-F11),2) | H11: =ROUND(G11*'Parameters'!$B$3,2) | I11: =G11+H11 | J11: =IF(D11=0,0,ROUND(G11/D11,2))
A12: SO-0010 | B12: 46157 | C12: West | D12: 20 | E12: 216.49 | F12: 0 | G12: =ROUND(D12*E12*(1-F12),2) | H12: =ROUND(G12*'Parameters'!$B$3,2) | I12: =G12+H12 | J12: =IF(D12=0,0,ROUND(G12/D12,2))
A13: SO-0011 | B13: 46314 | C13: North | D13: 2 | E13: 40.48 | F13: 0.15 | G13: =ROUND(D13*E13*(1-F13),2) | H13: =ROUND(G13*'Parameters'!$B$3,2) | I13: =G13+H13 | J13: =IF(D13=0,0,ROUND(G13/D13,2))
A14: SO-0012 | B14: 46043 | C14: North | D14: 12 | E14: 106.73 | F14: 0 | G14: =ROUND(D14*E14*(1-F14),2) | H14: =ROUND(G14*'Parameters'!$B$3,2) | I14: =G14+H14 | J14: =IF(D14=0,0,ROUND(G14/D14,2))
... A222: SO-0220 | B222: 46099 | C222: West | D222: 6 | E222: 184.25 | F222: 0 | G222: =ROUND(D222*E222*(1-F222),2) | H222: =ROUND(G222*'Parameters'!$B$3,2) | I222: =G222+H222 | J222: =IF(D222=0,0,ROUND(G222/D222,2))
