Workbook

Sheet Read Me
A1: Air Pollution Control Cost Estimation Spreadsheet
A2: For Carbon Adsorbers
A3: U.S. Environmental Protection Agency
A4: Air Economics Group
A5: Health and Environmental Impacts Division
A6: Office of Air Quality Planning and Standards
A7: (November 2020)
B9: This spreadsheet allows users to estimate the capital and annualized costs for installing and operating carbon adsorbers to control emissions of volatile organic compounds (VOCs) and hazardous air pollutants (HAP) from industrial waste gas streams. Carbon adsorbers are a non-destructive control technology employed to remove volatile organic compounds (VOCs) from low to medium concentration gas streams. Adsorption is generally used when a stringent outlet concentration must be met and/or when recovery of the VOC is desired. Carbon adsorbers may be operated in either intermittent or continuous modes. The carbon is regenerated by desorbing the VOC from the carbon. This can be done off-site or onsite. The basic equipment required for a carbon adsorber system includes one or more carbon vessels or canisters and auxiliary equipment, such as duct work, pumps and storage vessels to collect VOC desorbed from the activated carbon. The desorbed VOC can be reused onsite, sold to a recycler or disposed.
B11: The calculation methodologies used in this spreadsheet are those presented in the U.S. EPA's Air Pollution Control Cost Manual. This spreadsheet is intended to be used in combination with the Control Cost Manual. For a detailed description of the technology and cost methodology, see Section 3.1 (VOC Recapture Controls), Chapter 1 (Carbon Adsorbers) of the Air Pollution Control Cost Manual (as updated in 2018). Additional control technologies may be necessary for some industrial waste gas streams. Costs for additional control technologies can be estimated using the methods provided in other chapters of the cost manual. A copy of the Control Cost Manual is available on the U.S. EPA's "Technology Transfer Network" website at: https://www.epa.gov/economic-and-cost-analysis-air-pollution-regulations/cost-reports-and-guidance-air-pollution.
B13: The spreadsheet can be used to estimate capital and annualized costs for three types of carbon adsorbers: fixed-bed carbon adsorbers with steam regeneration; large carbon canisters with carbon replacement, and small carbon canisters with canister replacement. The methodology is designed to provide study-level (+-30%) cost estimates. Actual costs, particularly those for installation, can deviate significantly from the costs generated using this spreadsheet due to site conditions. Units of measures in this spreadsheet are English units.
B15: Instructions
B16: Step 1: Please select the Data Inputs tab and click on the Reset Form button. This will reset the values on the Data Inputs tab.
B17: Step 2: Use the drop down menus on the Data Inputs tab to select the type of carbon adsorber system (i.e., fixed-bed or canister). For fixed-bed adsorbers, use the drop down menus to enter the operating method (i.e., continuous or intermittent), material used for adsorber vessel fabrication and to specify whether the vessels are horizontal or vertical.
B18: Step 3: Complete all of the yellow data entry cells on the Data Inputs tab. Many of the fields are pre-populated with default values. Where possible, replace default values provided with site-specific values in accordance with the recommendations provided in the Control Cost Manual. Use of actual values other than the default values in this spreadsheet is recommended. Sources for all values used should be appropriately documented.
B19: Step 4: Once all of the data fields are complete, select the Design Parameters tab to see the calculated design parameters for your condenser. Select the Cost Estimate tab to view the estimated installation and operation costs for the carbon adsorber.

Sheet Data Inputs
C1: Data Inputs | L1: 3 | M1: Carbon Canister Adsorber with Canister Replacement | R1: =IF(L1=1,M1,(IF(L1=2,M2,M3))) -> Fixed-Bed Carbon Adsorber with Steam Regeneration
A2: Select the type of carbon adsorber system: | M2: Carbon Canister Adsorber with Carbon Replacement
M3: Fixed-Bed Carbon Adsorber with Steam Regeneration
A4: For fixed-bed carbon adsorbers, provide the following information: | O4: Cell L4= | P4: Fm Value
A5: Select the type of operation: | L5: 2 | M5: Not Applicable | O5: 1 | P5: 0 | Q5: =IF($L$5=1, 0, 0) -> 0 | R5: =IF($L$5=1, "Not Applicable"," ")
A6: Select the type of material used to fabricate the carbon adsorber vessels: | M6: Stainless Steel, 304 | O6: 2 | P6: 1 | Q6: =IF($L$5=2, 1, 0) -> 1 | R6: =IF($L$5=2, "(* Stainless Steel, 304)", " ") -> (* Stainless Steel, 304)
A7: Select the orientation for the adsorber vessels: | M7: Stainless Steel, 316 | O7: 3 | P7: 1.3 | Q7: =IF($L$5=3, 1.3, 0) -> 0 | R7: =IF($L$5=3, "(* Stainless Steel, 316)", " ")
M8: Carpenter 20 CB-3 | O8: 4 | P8: 1.9 | Q8: =IF($L$5=4, 1.9, 0) -> 0 | R8: =IF($L$5=4, "(* Carpenter 20 CB-3)", " ")
A9: ="Enter the design data for the proposed "&R1 -> Enter the design data for the proposed Fixed-Bed Carbon Adsorber with Steam Regeneration | M9: Monel-400 | O9: 5 | P9: 2.3 | Q9: =IF($L$5=5, 2.3, 0) -> 0 | R9: =IF($L$5=5, "(* Monel-400)", " ")
M10: Nickel-200 | O10: 6 | P10: 3.2 | Q10: =IF($L$5=6,3.2, 0) -> 0 | R10: =IF($L$5=6, "(* Nickel-200)", " ")
A11: Number of operating hours per year (Ɵs) | B11: 8640 | C11: hours/year | M11: Titanium | O11: 7 | P11: 4.5 | Q11: =IF($L$5=7,4.5, 0) -> 0 | R11: =IF($L$5=7, "(* Titanium)", " ")
A12: Waste Gas Flow Rate (Q) | B12: 10000 | C12: acfm* | D12: *acfm is actual cubic feet/min
A13: VOC Emission Rate (mvoc) | B13: 100 | C13: lbs/hour | M13: Fm = | P13: =SUM(Q5:Q11) -> 1
P14: =R5&R6&R7&R8&R9&R10&R11 -> (* Stainless Steel, 304)
A15: Required VOC removal efficiency (E) | B15: 98 | C15: ="percent"&(IF(B15=98, "*","")) -> percent* | D15: =IF(B15=98,"* 98 percent is a default control efficiency. User should enter actual value, if known."," ") -> * 98 percent is a default control efficiency. User should enter actual value, if known. | L15: 2 | M15: Not Applicable | P15: =IF(L15=1, "Not Applicable", IF(L15=2,"Horizontal", "Vertical")) -> Horizontal
A16: Superficial Bed Velocity (vb) | B16: 75 | C16: ft/min | D16: =IF(B16=0.65,"* 0.65 Btu/lb-mole-°F is a default value. User should enter actual value, if known."," ") | M16: Horizontal
A17: ="Estimated equipment life of"&(IF(L1>1," adsorber vessels and auxiliary Equipment (n)"," auxiliary Equipment (n)")) -> Estimated equipment life of adsorber vessels and auxiliary Equipment (n) | B17: 15 | C17: ="Years"&IF(B17=15,"*","") -> Years* | D17: =IF(AND(B17=15,L1>1),"* 15 years is a default equipment life. User should enter actual value, if known.",(IF(AND(B17=10,L1=1), "*10 years is a default equipment life. User should enter actual value , if known."))) -> * 15 years is a default equipment life. User should enter actual value, if known. | M17: Vertical
A18: Estimated Carbon life (n) | B18: 5 | C18: Years
A19: Total Number of carbon beds (Ntotal) | B19: 3 | C19: =IF(B19=3,"Beds*", "Beds") -> Beds* | D19: =IF(B19=3,"* 3 beds is the default. User should enter actual number of beds, if known."," ") -> * 3 beds is the default. User should enter actual number of beds, if known. | L19: 2 | M19: Not Applicable | P19: =IF(L19=2, "Continuous Operation", (IF(L19=3, "Intermittent Operation", "Not Applicable"))) -> Continuous Operation
A20: Number of carbon beds adsorbing VOC when system is operating (NA) | B20: 2 | C20: =IF(B20=2,"Beds*", "Beds") -> Beds* | D20: =IF(B20=2,"* 2 beds is the default. User should enter actual number of beds, if known."," ") -> * 2 beds is the default. User should enter actual number of beds, if known. | M20: Continuous Operation
A21: Total time for adsorption (ƟA) | B21: 12 | C21: =IF(B21=12,"hours*", "hours") -> hours* | D21: =IF(B21=12,"* 12 hours is a default value. User should enter actual value, if known."," ") -> * 12 hours is a default value. User should enter actual value, if known. | M21: Intermittent Operation
A22: Total time for desorption (ƟD) | B22: 5 | C22: =IF(B22=5,"hours*", "hours") -> hours* | D22: =IF(B22=5,"* 5 hours is a default value. User should enter actual value, if known."," ") -> * 5 hours is a default value. User should enter actual value, if known.
A23: Estimated Carbon Replacement Rate (CRR) | B23: 379 | C23: =IF(B23=379,"lbs/hour*","lbs/hour") -> lbs/hour* | D23: =IF(B23=379,"* 379 lbs./hour is a default value. User should enter actual value, if known."," ") -> * 379 lbs./hour is a default value. User should enter actual value, if known.
A24: Carbon Canister Size | B24: 3000 | C24: =IF(B24=3000,"lbs carbon per canister*", "lbs of carbon per canister") -> lbs carbon per canister* | D24: =IF(B24=3000,"* 3000 lbs of carbon per canister is a default value. User should enter prefered canister size, if known."," ") -> * 3000 lbs of carbon per canister is a default value. User should enter prefered canister size, if known.
A25: Number of Operating Hours Before Carbon Canister Replacement (ƟA) | B25: 4380 | C25: hours
A27: Enter the Characteristics of the VOC/HAP:
A29: Name of VOC/HAP | B29: Toluene
A30: ="Partial Pressure of "&B29&" in waste gas stream" -> Partial Pressure of Toluene in waste gas stream | B30: 0.0104 | C30: psia
A31: ="Parameter ""k"" for "&B29 -> Parameter "k" for Toluene | B31: 0.551 | C31: Note:
A32: ="Parameter ""m"" for "&B29 -> Parameter "m" for Toluene | B32: 0.11 | C32: Typical values of "k" and "m" for some common VOCs are shown in Table A.
A34: Enter the cost data for the carbon adsorber:
A36: Desired dollar-year | B36: 2018
A37: ="CEPCI* for " & B36 -> CEPCI* for 2018 | B37: 567.5 | C37: ="CEPCI value for "&B36 -> CEPCI value for 2018 | E37: 390.6 | F37: 1999
A38: Annual Interest Rate (i) | B38: 5 | C38: =(IF(B38<>5,"percent (Current bank prime rate)","percent*")) -> percent* | D38: =IF(B38=5,"* 5 percent is a default value. User should enter current prime bank rate.", "") -> * 5 percent is a default value. User should enter current prime bank rate.
A40: * CEPCI is the Chemical Engineering Plant Cost Index. The use of CEPCI in this spreadsheet is not an endorsement of the index for purpose of cost escalation or de-escalation, but is there merely to allow for availability of a well-known cost index to spreadsheet users. Use of other well-known cost indexes (e.g., M&S) is acceptable.
A42: Carbon Canister Cost | B42: 13400 | C42: ="per canister (in "&B36&" dollars)" -> per canister (in 2018 dollars) | D42: Note: Typical costs for carbon canisters are shown in Table B.
A43: Electricity (Pelec) | B43: 0.0676 | C43: ="per kWh"&IF(B43=0.0676, "*","") -> per kWh* | D43: =IF(B43=0.0676,"* $0.0676/kWh is a default value. User should enter actual value, if known.","") -> * $0.0676/kWh is a default value. User should enter actual value, if known.
A44: Steam (Ps) | B44: 5 | C44: ="per 1,000 lbs"&IF(B44=5, "*","") -> per 1,000 lbs* | D44: =IF(B44=5,"* $5.00/1,000 lbs is a default value. User should enter actual value, if known.","") -> * $5.00/1,000 lbs is a default value. User should enter actual value, if known.
A45: Cooling Water (Pcw) | B45: 3.55 | C45: ="per 1,000 gallons of water"&IF(B45=3.55, "*","") -> per 1,000 gallons of water* | D45: =IF(B45=3.55,"* $3.55/1,000 gallons is a default value. User should enter actual value, if known.","") -> * $3.55/1,000 gallons is a default value. User should enter actual value, if known.
A46: Operator Labor Rate | B46: 27.48 | C46: ="per hour"&IF(B46=27.48,"*","") -> per hour* | D46: =IF(B46=27.48,"* $27.48/hour is a default value. User should enter actual value, if known.","") -> * $27.48/hour is a default value. User should enter actual value, if known.
A47: Maintenance Labor Rate | B47: 30.23 | C47: ="per hour"&IF(B47=30.23,"*","") -> per hour* | D47: =IF(B47=30.23,"* $30.23/hour is a default value. User should enter actual value, if known. If the rate is not known, use 1.10 x operator labor rate.","") -> * $30.23/hour is a default value. User should enter actual value, if known. If the rate is not known, use 1.10 x operator labor rate.
A48: Carbon Cost (CC) | B48: 4.2 | C48: ="per lb"&IF(B48=1.9,"*","") -> per lb | D48: =IF(B48=4.2,"* $4.20/lb is a default value based on 2018 market price. User should enter actual value, if known.","") -> * $4.20/lb is a default value based on 2018 market price. User should enter actual value, if known.
A50: Re-Sale Value of Recovered VOC (Pvoc) | B50: 0.33 | C50: ="per lb"&IF(B50=0.33,"*","") -> per lb* | D50: =IF(B50=0.33,"* $0.33/lb is a default value for recovered toluene based on 2018 data. User should enter actual value of recovered VOC/HAP, if known. Enter zero if the recovered VOC/HAP cannot be sold or re-used onsite.","") -> * $0.33/lb is a default value for recovered toluene based on 2018 data. User should enter actual value of recovered VOC/HAP, if known. Enter zero if the recovered VOC/HAP cannot be sold or re-used onsite.
A51: Disposal/Treatment Cost for Recovered VOC (Dvoc) | B51: 0 | C51: ="per lb"&IF(B51=0,"*","") -> per lb* | D51: =IF(B51=0,"* $0/lb is a default value for disposal and/or treatment of recovered VOC/HAP. User should enter actual value, if known. Enter zero if the recovered VOC/HAP can be sold or re-used onsite without additional treatment.","") -> * $0/lb is a default value for disposal and/or treatment of recovered VOC/HAP. User should enter actual value, if known. Enter zero if the recovered VOC/HAP can be sold or re-used onsite without additional treatment.
A53: If known, enter any additional costs for site preparation and building construction/modification:
A54: Site Preparation (SP) = | B54: 0 | C54: =IF(B54=0, "* Default value. User should enter actual value, if known."," ") -> * Default value. User should enter actual value, if known.
A55: Buildings (Bldg) = | B55: 0 | C55: =IF(B55=0, "* Default value. User should enter actual value, if known."," ") -> * Default value. User should enter actual value, if known.
A56: Equipment Costs for auxiliary equipment (e.g., ductwork, dampers, and stack) (ECaux) = | B56: 32000 | C56: =IF(OR(B56=32000,B56=2000), "* Default value. User should enter actual value, if known."," ") -> * Default value. User should enter actual value, if known.
A57: Contingency Factor (CF) | B57: 10 | C57: ="percent"&IF(B57=10,"*","") -> percent* | D57: =IF(B57=10,"* 10 percent is a default value. The contingency factor should be between 5 and 15 percent.","") -> * 10 percent is a default value. The contingency factor should be between 5 and 15 percent.
A60: Data Sources for Default Values Used in Calculations:
A62: Data Element | B62: Default Value | C62: Sources for Default Value | E62: If you used your own site-specific values, please reference the source from which the site-specific value was derived. | J62: Recommended data sources for site-specific information
A63: Carbon Cost ($/lb) | B63: 1.9 | C63: January 2018 market price for virgin carbon. | J63: Check with activated carbon vendors for current prices.
A64: Operator Labor Rate ($/hour) | B64: 27.48 | C64: Bureau of Labor Statistics, May 2017 National Occupational Employment and Wage Estimates – United States, May 2017 (https://www.bls.gov/oes/current/oes_nat.htm). Hourly rates for operators based on data for plant and System Operators – other (51-8099). | J64: Use payroll data, if available, or check current edition of the Bureau of Labor Statistics, National Occupational Employment and Wage Estimates – United States (https://www.bls.gov/oes/current/oes_nat.htm).
A65: Maintenance Labor Rate ($/hour) | B65: 30.23 | C65: Estimated as 110 percent of operator labor rate. | J65: Use payroll data, if available, or check current edition of the Bureau of Labor Statistics, National Occupational Employment and Wage Estimates – United States (https://www.bls.gov/oes/current/oes_nat.htm).
A66: Value of Recovered VOC ($/lb.) | B66: 0.33 | C66: January 2018 market price for recovered toluene. | J66: Check with reagent vendors for current prices.
A67: Disposal/Treatment Cost for Recovered VOC ($/lb) | B67: 0 | C67: No additional treatment or disposal costs - Recovered VOC can be sold to a solvent recovery company. | J67: Check with reagent recyclers for current prices or enter estimated costs for onsite treatment, as applicable.
A68: Steam ($/1,000 lb) | B68: 5 | C68: Price of steam was estimated by multiplying the average price of natural gas for industrial facilities ($4.00/MMBtu) by 1.3 and converting to $/1,000 lb of steam. Natural gas price is the 2017 average price for industrial facilities published by the U.S. Department of Energy, Energy Information Administration (see https://www.eia.gov/dnav/ng/ng_pri_sum_dcu_nus_a.htm). | J68: Use actual values if known, or estimate steam cost as 1.3 x Fuel Cost for oil and gas-fired facilities. See also Department of Energy, Energy Efficiency and Renewable Energy, A Best Practices Steam Technical Brief: How to Calculate the True Cost of Steam, DOE/GO-102003-1736, September 2003 (available at https://www.energy.gov/sites/prod/files/2014/05/f15/tech_brief_true_cost.pdf).
A69: Cooling Water ($/1,000 gallons) | B69: 3.55 | C69: Average water rates for industrial facilities in 2013, compiled by Black & Veatch. (see 2012/2013 "50 Largest Cities Water/Wastewater Rate Survey." Available at http://www.saws.org/who_we_are/community/RAC/docs/2014/50-largest-cities-brochure-water-wastewater-rate-survey.pdf. | J69: Use actual values if known, or estimate steam cost as 1.3 x Fuel Cost for oil and gas-fired facilities. See also Department of Energy, Energy Efficiency and Renewable Energy, A Best Practices Steam Technical Brief: How to Calculate the True Cost of Steam, DOE/GO-102003-1736, September 2003 (available at https://www.energy.gov/sites/prod/files/2014/05/f15/tech_brief_true_cost.pdf).
A70: Electricity Cost ($/kWh) | B70: 0.0676 | C70: Average annual electricity cost for industrial plants is based on 2017 price data compiled by the U.S. Energy Information Administration from data reported on Form EIA-861 and 861S, (http://www.eia.gov/electricity/data.cfm#sales). | J70: Plant's utility bill or use U.S. Energy Information Administration (EIA) data for most recent year. Available at http://www.eia.gov/electricity/data.cfm#sales.

Sheet Design Parameters
A1: Design Parameters
A3: The following design parameters for the carbon adsorber were calculated based on the values entered on the Data Inputs tab. These values were used to prepare the costs shown on the Cost Estimate tab.
A4: Type of Carbon Adsorber: | B4: ='Data Inputs'!R1 -> Fixed-Bed Carbon Adsorber with Steam Regeneration
A5: Name of VOC Controlled: | B5: ='Data Inputs'!B29 -> Toluene
A7: Parameter | B7: Equation | C7: Calculated Value | D7: Units
A8: =IF('Data Inputs'!B29=" ", "Quantity of VOC Recovered:", IF('Data Inputs'!L1<3,"Quantity of "&'Data Inputs'!B29&" Removed:","Quantity of "&'Data Inputs'!B29&" Recovered:" )) -> Quantity of Toluene Recovered:
A9: =IF('Data Inputs'!B29=" ","Quantity of VOC Recovered (Wvoc) =",IF('Data Inputs'!L1<3,"Quantity of "&'Data Inputs'!B29&" Removed (Wvoc) =","Quantity of "&'Data Inputs'!B29&" Recovered (Wvoc) =")) -> Quantity of Toluene Recovered (Wvoc) = | B9: Wvoc = mvoc x Ɵs x E = | C9: =('Data Inputs'!B13*'Data Inputs'!B11*('Data Inputs'!B15/100))/2000 -> 423.36 | D9: tons/year
A10: Time required for Desorption (ƟD) = | C10: ='Data Inputs'!B22 -> 5 | D10: hours
A11: Time for Adsorption (ƟA) = | C11: ='Data Inputs'!B21 -> 12 | D11: hours
A12: Time Available for Desorption = | B12: ƟA (ND/NA) = | C12: =C11*C19/C20 -> 6 | D12: hours
C13: =IF(C10>C12, "* Warning: Time required for desorption is less than the amount of time available.", " ")
A15: Adsorber Parameters:
A16: Equilibrium Capacity at the Inlet (We(max)) = | B16: k x Pm = | C16: ='Data Inputs'!B31*('Data Inputs'!B30)^'Data Inputs'!B32 -> 0.33344581 | D16: lb. VOC/lb. Carbon
A17: Working Capacity (wc) = | B17: 0.5 x we(max) = | C17: =0.5*C16 -> 0.16672291 | D17: lb. VOC/lb. Carbon
A18: Adjustment Factor for Adorber Vessel Material (Fm ) = | C18: ='Data Inputs'!P13 -> 1 | D18: ='Data Inputs'!P14 -> (* Stainless Steel, 304)
A19: Number of Bed Desorbing (ND) = | B19: Ntotal - NA = | C19: ='Data Inputs'!B19-'Data Inputs'!B20 -> 1 | D19: Bed
A20: Number of Bed Adsorbing (NA) = | C20: ='Data Inputs'!B20 -> 2 | D20: Bed
A22: Volumetric Flow Rate for each Vessel (Q') = | B22: Q/NA = | C22: ='Data Inputs'!B12/'Design Parameters'!C20 -> 5000 | D22: acfm/Bed
A23: Carbon Bed Thickness (tb) = | B23: (Mc'/ρb)/(Q'/vb), where the density of carbon (ρb) = 30 lb/sq.ft | C23: =(C29/30)/(C22/'Data Inputs'!B16) -> 1.7993928 | D23: ft.
A24: Pressure Drop (ΔPs) = | B24: tb x (0.03679vb +1.107x10-4vb2) + 1 = | C24: =1+(C23*((0.03679*'Data Inputs'!B16)+((0.0001107)*('Data Inputs'!B16^2)))) -> 7.0854341 | D24: inches
A25: Cooling Fan Operating Time (Ɵcf) = | B25: 0.4 x ƟD x (NA x Ɵs)/ƟA = | C25: =0.4*C10*(C20*'Data Inputs'!B11)/'Design Parameters'!C11 -> 2880 | D25: hours
A26: Estimated Carbon Required:
A27: Estimated Carbon Consumption (Mc) for a continuously operated system = | B27: (mvoc/wc) x ƟA (1 + ND/NA) = | C27: =('Data Inputs'!B13/C17)*'Data Inputs'!B21*(1+'Design Parameters'!C19/'Design Parameters'!C20) -> 10796.357 | D27: lbs.
A28: Estimated Carbon Consumption (Mc) for an intermittently operated system = | B28: (mvoc/wc) x ƟA = | C28: =('Data Inputs'!B13/'Design Parameters'!C17)*'Data Inputs'!B21 -> 7197.5713 | D28: lbs.
A29: Carbon Required for each Vessel (Mc') = | B29: Mc /(NA + ND) = | C29: =IF('Data Inputs'!L19=2,(C27/(C19+C20)),IF('Data Inputs'!L19=3,(C28),0)) -> 3598.7856 | D29: lbs./Bed
A31: Estimated Adsorber Vessel Dimensions and Surface Area:
A32: Vessel Orientation = | C32: ='Data Inputs'!P15 -> Horizontal
A33: Vessel Diameter (D) = | B33: (0.127 x Mc' x vb)/Q' = | C33: =(0.127*C29*'Data Inputs'!B16)/C22 -> 6.8556867 | D33: ft.
A34: Vessel Length (L) = | B34: (7.87/Mc') x (Q'/vb)2 = | C34: =(7.87/C29)*(C22/'Data Inputs'!B16)^2 -> 9.7193279 | D34: ft.
A35: Surface Area of Adsorber Vessel (S) = | B35: π x D x (L+D/2) = | C35: =PI()*C33*(C34+C33/2) -> 283.16081 | D35: sq.ft
A36: Vessel Diameter (D) = | B36: (4Q'/πvb) = | C36: =((4*C22)/(PI()*'Data Inputs'!B16))^0.5 -> 9.2131773 | D36: ft.
A37: Vessel Length (L) = | B37: tb + ta,g = | C37: =C23+4 -> 5.7993928 | D37: ft.
A38: Surface Area of Adsorber Vessel (S) = | B38: π x D x (L+D/2) = | C38: =PI()*C36*(C37+C36/2) -> 301.19125 | D38: sq.ft
A40: Electricity Consumption:
A41: Electricity Consumed by the system fan (Qsf) = | B41: (0.746kW/hp) x 2.5x10-4 x Q x ΔPs x Ɵs = | C41: =0.746*(0.00025)*C24*'Data Inputs'!B12*'Data Inputs'!B11 -> 114171.85 | D41: kWh/year
A42: Electricity Consumed by the cooling fan (Qcf) = | B42: (0.746kW/hp) x 2.5x10-4 x Qcf x ΔPs x Ɵcf = | C42: =0.746*(0.00025)*C24*3000*C25 -> 11417.185 | D42: kWh/year
A43: Electricity Consumed by the Cooling Water Fan (Qcwf) = | B43: (0.746kW/hp) x [2.52x10-4 x 100/η] x [Ɵcwp /(0.6 x ƟD x NA x ƟD/ƟA )x 60 mins/hour] = | C43: =(0.746)*((0.000252*100)/0.63)*(C51/((0.6*C10*C20*'Data Inputs'!B11)/'Design Parameters'!C11)*60) -> 4298.7504 | D43: kWh/year
A44: Total Estimated Electricity Consumption (QElec) = | B44: Qsf + Qcf + Qcsf = | C44: =C41+C42+C43 -> 129887.79 | D44: kWh/year
A46: Steam Consumption:
A47: Total Steam Consumption (QSteam) = | B47: = 3.5 x Mvoc x Ɵs = | C47: =3.5*'Data Inputs'!B13*'Data Inputs'!B11 -> 3024000 | D47: lbs./year
A50: Cooling Water Consumption:
A51: Total Cooling Water Consumption (Qcw) = | B51: = 3.43 x Cs/Ps = | C51: =C47*3.43 -> 10372320 | D51: gallons/year
A54: Number of times canister(s) replaced per year = | B54: Ɵs / ƟA = | C54: ='Data Inputs'!B11/'Data Inputs'!B25 -> 1.9726027
A56: Adsorber Parameters for Carbon Canisters:
A57: Time for Adsorption (ƟA) = | B57: Number of operating hours before carbon canister replacement = | C57: ='Data Inputs'!B25 -> 4380 | D57: hours
A58: Equilibrium Capacity at the Inlet (We(max)) = | B58: k x Pm = | C58: ='Data Inputs'!B31*('Data Inputs'!B30)^'Data Inputs'!B32 -> 0.33344581 | D58: lb. VOC/lb. Carbon
A59: Working Capacity (wc) = | B59: 0.5 x we(max) = | C59: =0.5*C58 -> 0.16672291 | D59: lb. VOC/lb. Carbon
A60: Estimated Total Carbon Required (Mc) = | B60: (mvoc/wc) x ƟA = | C60: =('Data Inputs'!B13/'Design Parameters'!C58)*C57 -> 1313556.8 | D60: lbs.
A61: Number of Carbon Canisters Required = | B61: Mc/Carbon Canister Capacity | C61: =ROUNDUP((C60/'Data Inputs'!B24),0.1) -> 438 | D61: canisters
A62: ="Total Quantity of Carbon Required for "&C61&" Canisters =" -> Total Quantity of Carbon Required for 438 Canisters = | B62: Number of Carbon Canisters * Carbon Capacity per Canister = | C62: =C61*'Data Inputs'!B24 -> 1314000 | D62: lbs.
A63: Capital Recovery Factor:
A64: ="Capital Recovery Factor for "&(IF('Data Inputs'!L1>1,"adsorber vessels and auxiliary equipment (CFRabsorber)=","auxiliary equipment (CFRaux) =")) -> Capital Recovery Factor for adsorber vessels and auxiliary equipment (CFRabsorber)= | B64: [i × (1 + i)n] / [(1 + i)n - 1] = | C64: =(('Data Inputs'!B38/100)*(1+('Data Inputs'!B38/100))^'Data Inputs'!B17)/(((1+('Data Inputs'!B38/100))^'Data Inputs'!B17)-1) -> 0.096342288
B65: Where n = Equipment Life and i = Interest Rate
A66: Capital Recovery Factor for carbon (CRFCarbon) = | B66: [i × (1 + i)n] / [(1 + i)n - 1] = | C66: =((('Data Inputs'!B38/100)*(1+('Data Inputs'!B38/100))^'Data Inputs'!B18)/(((1+('Data Inputs'!B38/100))^'Data Inputs'!B18)-1)) -> 0.2309748
B67: Where n = Carbon Life and i = Interest Rate
A68: Capital Recovery Factor for carbon (CRFCarbon canister) = | B68: [i × (1 + i)n] / [(1 + i)n - 1] = | C68: =IF(C54>1, "Not applicable: Canisters are replaced "&C54&" times/year", ((('Data Inputs'!B38/100)*(1+('Data Inputs'!B38/100))^(1/C54))/(((1+('Data Inputs'!B38/100))^(1/C54))-1))) -> Not applicable: Canisters are replaced 1.97260273972603 times/year
B69: Where n = Carbon Canister Life and i = Interest Rate

Sheet Cost Estimate
A1: Cost Estimate | L1: 3
A3: Capital Costs
A5: ="Estimated capital costs for a "&'Data Inputs'!R1&" with the following characteristics:" -> Estimated capital costs for a Fixed-Bed Carbon Adsorber with Steam Regeneration with the following characteristics: | L5: 2
A6: VOC Controlled/Recovered = | B6: ='Data Inputs'!B29 -> Toluene
A7: Adsorber Vessel Orientation = | B7: ='Data Inputs'!P15 -> Horizontal
A8: Operating Schedule = | B8: ='Data Inputs'!P19 -> Continuous Operation
A10: ="Total Capital Investment (TCI) (in "&'Data Inputs'!B36&" dollars)" -> Total Capital Investment (TCI) (in 2018 dollars)
A11: Parameter | B11: Equation | C11: Cost
A12: Costs for Each Carbon Adsorber Vessel (Cv) = | B12: 271 x Fm x S0.778 = | C12: =271*'Design Parameters'!C18*(IF('Data Inputs'!L15=2, ('Design Parameters'!C35^0.778), IF('Data Inputs'!L15=3, ('Design Parameters'!C38^0.778), 0)))*('Data Inputs'!B37/'Data Inputs'!E37) -> 31833.523
A13: Total Cost for All Carbon Adsorber Vessels and Carbon(ECAdsorb) = | B13: 5.82 x Q-0.133 x [Cc + (NA + ND) x Cv] = | C13: =5.82*('Data Inputs'!B12^-0.133)*(('Data Inputs'!B48*'Design Parameters'!C27)+(('Design Parameters'!C19+'Design Parameters'!C20)*C12)) -> 240804.86
A14: Auxiliary Equipment (ECaux) = | B14: (Based on design costs or estimated using methods provided in Section 2) | C14: ='Data Inputs'!B56 -> 32000
A15: Total Purchased Equipment Costs for Carbon Adsorber (A) = | B15: = ECAdsorb + ECaux = | C15: =C13+C14 -> 272804.86 | L15: 2 | P15: Horizontal
A17: Instrumentation = | B17: 0.10 × A = | C17: Included in A
A18: Sales taxes = | B18: 0.03 × A = | C18: =0.03*C15 -> 8184.1458
A19: Freight = | B19: 0.05 × A = | C19: =0.05*C15 -> 13640.243 | L19: 2
A21: Total Purchased Equipment Costs (B) = | C21: =C15+C18+C19 -> 294629.25
A23: ="Direct Installation Costs (in "&'Data Inputs'!B36&" dollars)" -> Direct Installation Costs (in 2018 dollars)
A24: Parameter | B24: Equation | C24: Cost
A25: Foundations and Supports = | B25: 0.08 × B = | C25: =0.08*C21 -> 23570.34
A26: Handling and Erection = | B26: 0.14 × B = | C26: =0.14*C21 -> 41248.095
A27: Electrical = | B27: 0.04 × B = | C27: =0.04*C21 -> 11785.17
A28: Piping = | B28: 0.02 × B = | C28: =0.02*C21 -> 5892.585
A29: Insulation = | B29: 0.01 × B = | C29: =0.01*C21 -> 2946.2925
A30: Painting = | B30: 0.01 × B = | C30: =0.01*C21 -> 2946.2925
A31: Site Preparation (SP) = | C31: ='Data Inputs'!B54 -> 0
A32: Buildings (Bldg) = | C32: ='Data Inputs'!B55 -> 0
B34: Total Direct Costs (DC) = B + (0.3 × B) + SP + Bldg = | C34: =SUM(C25:C32)+C21 -> 383018.02
A36: ="Total Indirect Installation Costs (in "&'Data Inputs'!B36&" dollars)" -> Total Indirect Installation Costs (in 2018 dollars)
A37: Parameter | B37: Equation | C37: Cost
A38: Engineering = | B38: 0.10 × B = | C38: =(0.1*C$21) -> 29462.925
A39: Construction and field expenses = | B39: 0.05 × B = | C39: =(0.05*C$21) -> 14731.462
A40: Contractor fees = | B40: 0.10 × B = | C40: =(0.1*C$21) -> 29462.925
A41: Start-up = | B41: 0.02 × B = | C41: =(0.02*C$21) -> 5892.585
A42: Performance test = | B42: 0.01 × B = | C42: =(0.01*C$21) -> 2946.2925
A44: Total Indirect Costs (IC) = | C44: =(SUM(C38:C42)) -> 82496.19
A45: Contingency Cost (C) = | B45: CF(IC+DC)= | C45: =(C34+C44)*('Data Inputs'!B57/100) -> 46551.421
A47: Total Capital Investment (TCI) = | B47: DC + IC + C = (1.28 × B) + SP + Bldg. + C = | C47: =C34+C44+C45 -> 512065.64 | D47: ="in "&'Data Inputs'!$B$36&" dollars" -> in 2018 dollars
A49: Annual Costs
A51: Direct Annual Costs
A52: Parameter | B52: Equation | C52: Cost
A53: Annual Electricity Cost = | B53: QElec × Pelec = | C53: ='Data Inputs'!B43*'Design Parameters'!C44 -> 8780.4143
A54: Annual Steam Cost (Cs) = | B54: 3.50 x mvoc x Ɵs x Ps = | C54: =('Design Parameters'!C47/1000)*'Data Inputs'!B44 -> 15120
A55: Annual Cooling Water Cost (Ccs) = | B55: 3.43 x Cs/Ps x Pwc = | C55: =('Design Parameters'!C51/1000)*'Data Inputs'!B45 -> 36821.736
A56: Operating Labor Costs: | B56: Operator = 0.5 hours/shift × Labor Rate × (Operating hours/8 hours/shift) | C56: =0.5*'Data Inputs'!B46*'Data Inputs'!B11/8 -> 14839.2
B57: Supervisor = 15% of Operator | C57: =(0.15*C56) -> 2225.88
A58: Maintenance Costs: | B58: Labor = 0.5 hours/shift × Labor Rate × (Operating Hours/8 hours/shift) | C58: =(0.5*'Data Inputs'!B47*'Data Inputs'!B11/8) -> 16324.2
B59: Materials = 100% of maintenance labor | C59: =C58 -> 16324.2
A60: Carbon Replacement Costs: | B60: Labor = CRFcarbon x (Labor Rate × Mc)/CRR = | C60: =IF(B8="Continuous Operation",'Design Parameters'!C66*(('Data Inputs'!B47*'Design Parameters'!C27)/'Data Inputs'!B23),'Design Parameters'!C66*(('Data Inputs'!B47*'Design Parameters'!C28)/'Data Inputs'!B23)) -> 198.90274
B61: Carbon = CRFcarbon x CC x Mc x 1.08 = | C61: =IF(B8="Continuous Operation",'Design Parameters'!C66*'Data Inputs'!B48*'Design Parameters'!C27*1.08, 'Design Parameters'!C66*'Data Inputs'!B48*'Design Parameters'!C27*1.08) -> 11311.361
A64: Direct Annual Costs (DAC) = | C64: =SUM(C53:C61) -> 121945.89 | D64: ="in "&'Data Inputs'!$B$36&" dollars" -> in 2018 dollars
A66: Indirect Annual Costs
A67: Parameter | B67: Equation | C67: Cost
A68: Overhead | B68: = 60% of sum of operator, supervisor, maintenance labor Plus maintenance materials | C68: =(0.6*(C56+C57+C58+C59)) -> 29828.088
A69: Administrative Charges | B69: = 2% of TCI | C69: =(0.02*C47) -> 10241.313
A70: Property Taxes | B70: = 1% of TCI | C70: =0.01*C47 -> 5120.6564
A71: Insurance | B71: = 1% of TCI | C71: =0.01*C47 -> 5120.6564
A72: Capital Recovery | B72: = CRFAdsorber × (TCI - [(1.08 x CC x Mc) + (LR x Mc/CRR)] = | C72: ='Design Parameters'!$C$64*(C47-((C61/'Design Parameters'!C66)+(C60/'Design Parameters'!C66))) -> 44532.509
A74: Indirect Annual Costs (IAC) = | C74: =SUM(C68:C72) -> 94843.223 | D74: ="in "&'Data Inputs'!$B$36&" dollars" -> in 2018 dollars
A76: Recovered Solvent Credit/Disposal Costs
A78: Disposal Cost
A79: Parameter | B79: Equation | C79: Cost
A80: VOC Disposal/Treatment Costs (Disposalcost) | B80: = mvoc x Ɵs x Dvoc x E = | C80: ='Design Parameters'!C9*2000*'Data Inputs'!B51 -> 0
A83: VOC Recovery Credit
A84: Parameter | B84: Equation | C84: Cost
A85: Annual Recovery Credit for Condensate (RC) | B85: = mvoc × Ɵs x Pvoc x E = | C85: ='Design Parameters'!C9*2000*'Data Inputs'!B50 -> 279417.6
A87: Total Annual Cost (TAC) = | B87: DAC + IAC + C + DisposalCost - RC = | C87: =C74+C64+C80-C85 -> -62628.483 | D87: ="in "&'Data Inputs'!$B$36&" dollars" -> in 2018 dollars
A89: Cost Effectiveness
A91: Cost Effectiveness
A92: Parameter | B92: Equation | C92: Cost
A93: Total Annual Cost = | B93: TAC = | C93: =C87 -> -62628.483 | D93: ="per year in "&'Data Inputs'!B36& " dollars" -> per year in 2018 dollars
A94: Annual Quantity of VOC Removed/Recovered = | B94: Wvoc = mvoc x Ɵs x E = | C94: ='Data Inputs'!B13*'Data Inputs'!B11*('Data Inputs'!B15/100)*(1/2000) -> 423.36 | D94: tons/year
A95: Cost Effectiveness = | B95: Total Annual Cost (TAC) / Annual Quantity of VOC Removed/Recovered = | C95: =C93/C94 -> -147.93198 | D95: ="per ton of pollutants removed/recovered in "&'Data Inputs'!B36& " dollars" -> per ton of pollutants removed/recovered in 2018 dollars
A97: Canisters with carbon replacement
A98: Total Cost for All Carbon Adsorber Canisters (ECAdsorb) = | B98: Canister Cost x Number of Canisters Required = | C98: ='Design Parameters'!C61*'Data Inputs'!B42 -> 5869200
A99: Auxiliary Equipment (ECaux) = | B99: (Based on design costs or estimated using methods provided in Section 2) | C99: ='Data Inputs'!B56 -> 32000
A100: Total Purchased Equipment Costs for Carbon Adsorber (A) = | B100: = ECAdsorb + ECaux = | C100: =C98+C99 -> 5901200
A102: Instrumentation = | B102: 0.10 × A = | C102: =0.1*C100 -> 590120
A103: Sales taxes = | B103: 0.03 × A = | C103: =0.03*C100 -> 177036
A104: Freight = | B104: 0.05 × A = | C104: =0.05*C100 -> 295060
A106: Total Purchased Equipment Costs (B) = | C106: =C100+C102+C103+C104 -> 6963416
A108: ="Installation Costs (in "&'Data Inputs'!B36&" dollars)" -> Installation Costs (in 2018 dollars)
A109: Parameter | B109: Equation | C109: Cost
A110: Direct and Indirect Installation = | B110: 0.20 × B = | C110: =0.08*C106 -> 557073.28
A111: Site Preparation (SP) = | C111: ='Data Inputs'!B133 -> 0
A112: Buildings (Bldg) = | C112: ='Data Inputs'!B134 -> 0
A114: Total Direct and Indirect Installation Costs = | C114: =(SUM(C110:C112)) -> 557073.28
A115: Contingency Cost (C) = | B115: CF(Purchase Equipment Cost + Installation costs)= | C115: =(C114+C106)*('Data Inputs'!B57/100) -> 752048.93
A117: Total Capital Investment (TCI) = | B117: Purchace Equipment Costs + Installation Costs + Contingency Costs = | C117: =C106+C114+C115 -> 8272538.2 | D117: ="in "&'Data Inputs'!$B$36&" dollars" -> in 2018 dollars
A119: Annual Costs
A121: Direct Annual Costs
A122: Parameter | B122: Equation | C122: Cost
A123: Operating Labor Costs: | B123: Operator = 0.5 hours/shift × Labor Rate × (Operating hours/8 hours/shift) | C123: =0.5*'Data Inputs'!B46*'Data Inputs'!B11/8 -> 14839.2
B124: Supervisor = 15% of Operator | C124: =(0.15*C123) -> 2225.88
A125: Maintenance Costs: | B125: Labor = 0.5 hours/shift × Labor Rate × (Operating Hours/8 hours/shift) | C125: =(0.5*'Data Inputs'!B47*'Data Inputs'!B11/8) -> 16324.2
B126: Materials = 100% of maintenance labor | C126: =C125 -> 16324.2
A127: Carbon Replacement Costs: | B127: Labor = CFRcarbon [Labor Rate × TC/CRR] = | C127: ='Design Parameters'!C66*'Data Inputs'!B46*'Design Parameters'!C62/'Data Inputs'!B23 -> 22005.816
B128: Carbon = CRFcarbon[CC x Tc x 1.08] = | C128: ='Design Parameters'!C66*'Data Inputs'!B48*'Design Parameters'!C62*1.08 -> 1376680
A131: Direct Annual Costs (DAC) = | C131: =SUM(C123:C128) -> 1448399.3 | D131: ="in "&'Data Inputs'!$B$36&" dollars" -> in 2018 dollars
A133: Indirect Annual Costs
A134: Parameter | B134: Equation | C134: Cost
...

Sheet Table A
A1: Table A: Typical Parameters for Selected Adsorption Isothermsa
A4: Compound | B4: Adsorption Temperature (°F) | C4: Isotherm Parameters | E4: Range of Isothermb
C5: k | D5: m | E5: (psia)
A6: Acetone | B6: 100 | C6: 0.412 | D6: 0.389 | E6: 0.0001 - 0.05
A7: Acrylonitrile | B7: 100 | C7: 0.935 | D7: 0.424 | E7: 0.0001 - 0.015
A8: Benzene | B8: 77 | C8: 0.597 | D8: 0.176 | E8: 0.0001 - 0.05
A9: Chlorobenzene | B9: 77 | C9: 1.05 | D9: 0.188 | E9: 0.0001 - 0.01
A10: Cyclohexane | B10: 100 | C10: 0.505 | D10: 0.21 | E10: 0.0001 - 0.05
A11: Dichloroethane | B11: 77 | C11: 0.976 | D11: 0.281 | E11: 0.0001 - 0.04
A12: m - Xylene | B12: 77 | C12: 0.708 | D12: 0.113 | E12: 0.0001 - 0.001
A13: Phenol | B13: 104 | C13: 0.855 | D13: 0.153 | E13: 0.0001 - 0.03
A14: Toluene | B14: 77 | C14: 0.551 | D14: 0.11 | E14: 0.001 - 0.05
A15: Trichloroethane | B15: 77 | C15: 1.06 | D15: 0.161 | E15: 0.0001 - 0.04
A16: Vinyl Chloride | B16: 100 | C16: 0.2 | D16: 0.477 | E16: 0.0001 - 0.05
A18: a Each isotherm is of the form w = kPm, where w is the equilibrium adsorptivity (lb adsorbated/lb adsorbant), P is the partial pressure of VOC in the gas stream (psia), and k and m are empirical parameters based on Calgon BPL carbon.
A19: b Adsorptivity equation should not be extrapolated outside these ranges.

Sheet Table B
A1: Table B: Typical Equipment Costs for Carbon Adsorber Canistersa
A3: Canister Size (in pounds of activated carbon) | B3: Maximum Flow Rate (cfm) | C3: Canister Type | D3: ="Cost with Virgin Carbon (in "&'Data Inputs'!B36&" dollars)" -> Cost with Virgin Carbon (in 2018 dollars) | E3: ="Cost with Reactivated Carbon (in "&'Data Inputs'!B36&" dollars)" -> Cost with Reactivated Carbon (in 2018 dollars) | K3: Cost with Virgin Carbon (in 2018 dollars) | L3: Cost with Reactivated Carbon (in 2018 dollars)
A4: 140 | B4: 500 | C4: Polyethylene | D4: =K4*('Data Inputs'!B$37/'Data Inputs'!E$37) -> 1046.0829 | E4: - | K4: 720 | L4: -
A5: 140 | B5: 500 | C5: Epoxy-Lined Steel | D5: =K5*('Data Inputs'!B$37/'Data Inputs'!E$37) -> 1605.4467 | E5: - | K5: 1105 | L5: -
A6: 170 | B6: 300 | C6: Epoxy-Lined Steel | D6: =K6*('Data Inputs'!B$37/'Data Inputs'!E$37) -> 1583.6534 | E6: - | K6: 1090 | L6: -
A7: 180 | B7: 100 | C7: Epoxy-Lined Steel | D7: =K7*('Data Inputs'!B$37/'Data Inputs'!E$37) -> 2324.6288 | E7: =L7*('Data Inputs'!B$37/'Data Inputs'!E$37) -> 1423.8351 | K7: 1600 | L7: 980
A8: 200 | B8: 100 | C8: Epoxy-Lined Steel | D8: =K8*('Data Inputs'!B$37/'Data Inputs'!E$37) -> 1140.521 | E8: - | K8: 785 | L8: -
A9: 1000 | B9: 600 | C9: Epoxy-Lined Steel | D9: =K9*('Data Inputs'!B$37/'Data Inputs'!E$37) -> 9589.0937 | E9: - | K9: 6600 | L9: -
A10: 1000 | B10: 1000 | C10: Epoxy-Lined Steel | D10: =K10*('Data Inputs'!B$37/'Data Inputs'!E$37) -> 16708.269 | E10: =L10*('Data Inputs'!B$37/'Data Inputs'!E$37) -> 10170.251 | K10: 11500 | L10: 7000
A11: 2000 | B11: 2000 | C11: Epoxy-Lined Steel | D11: =K11*('Data Inputs'!B$37/'Data Inputs'!E$37) -> 27604.967 | E11: =L11*('Data Inputs'!B$37/'Data Inputs'!E$37) -> 14528.93 | K11: 19000 | L11: 10000
A12: 2000 | B12: 750 | C12: Carbon Steel | D12: =K12*('Data Inputs'!B$37/'Data Inputs'!E$37) -> 31963.646 | E12: =L12*('Data Inputs'!B$37/'Data Inputs'!E$37) -> 19178.187 | K12: 22000 | L12: 13200
A13: 3000 | B13: 2000 | C13: Epoxy-Lined Steel | D13: =K13*('Data Inputs'!B$37/'Data Inputs'!E$37) -> 20195.212 | E13: - | K13: 13900 | L13: -
A14: 4100 | B14: 8000 | C14: Polypropylene | D14: =K14*('Data Inputs'!B$37/'Data Inputs'!E$37) -> 65380.184 | E14: - | K14: 45000 | L14: -
A15: 5000 | B15: 2500 | C15: Carbon Steel | D15: =K15*('Data Inputs'!B$37/'Data Inputs'!E$37) -> 61893.241 | E15: =L15*('Data Inputs'!B$37/'Data Inputs'!E$37) -> 29203.149 | K15: 42600 | L15: 20100
A16: 8000 | B16: 4500 | C16: Carbon Steel | D16: =K16*('Data Inputs'!B$37/'Data Inputs'!E$37) -> 95890.937 | E16: =L16*('Data Inputs'!B$37/'Data Inputs'!E$37) -> 43586.79 | K16: 66000 | L16: 30000
A17: 10000 | B17: 18000 | C17: Polypropylene | D17: =K17*('Data Inputs'!B$37/'Data Inputs'!E$37) -> 137298.39 | E17: - | K17: 94500 | L17: -
A18: (a) Equipment costs based on 2018 data provided by Calgon Carbon Corporation and Carbtrol Corporation.
