Workbook

Sheet c0_Records
C4: Units | D4: Unit Price | E4: Unit Cost | F4: Shipping | G4: Discount Rate | H4: Tax Rate | I4: Net Profit
C7: 11 | D7: 47 | E7: 8 | F7: 3 | G7: 0.1 | H7: 0.03 | I7: =C7*D7*(1-G7)*(1-H7)-C7*E7-F7
C8: 12 | D8: 48 | E8: 8 | F8: 3 | G8: 0.1 | H8: 0.03 | I8: =C8*D8*(1-G8)*(1-H8)-C8*E8-F8
C9: 13 | D9: 49 | E9: 8 | F9: 3 | G9: 0.1 | H9: 0.03 | I9: =C9*D9*(1-G9)*(1-H9)-C9*E9-F9
C10: 14 | D10: 50 | E10: 8 | F10: 3 | G10: 0.1 | H10: 0.03 | I10: =C10*D10*(1-G10)*(1-H10)-C10*E10-F10
C11: 15 | D11: 51 | E11: 8 | F11: 3 | G11: 0.1 | H11: 0.03 | I11: =C11*D11*(1-G11)*(1-H11)-C11*E11-F11
C12: 16 | D12: 52 | E12: 8 | F12: 3 | G12: 0.1 | H12: 0.03 | I12: =C12*D12*(1-G12)*(1-H12)-C12*E12-F12

Sheet c1_Records
AZ2: =D10*E10*(1-H10)*(1-I10)-D10*F10-G10
AZ3: =D11*E11*(1-H11)*(1-I11)-D11*F11-G11
C4: Net Profit | D4: Units | E4: Unit Price | F4: Unit Cost | G4: Shipping | H4: Discount Rate | I4: Tax Rate | AZ4: =D12*E12*(1-H12)*(1-I12)-D12*F12-G12
AZ5: =D7*E7*(1-H7)*(1-I7)-D7*F7-G7
AZ6: =D8*E8*(1-H8)*(1-I8)-D8*F8-G8
C7: =D7*E7*(1-H7)*(1-I7)+D7*F7-G7 | D7: 11 | E7: 47 | F7: 8 | G7: 3 | H7: 0.1 | I7: 0.03 | AZ7: =D9*E9*(1-H9)*(1-I9)-D9*F9-G9
C8: =D8*E8*(1-H8)*(1-I8)+D8*F8-G8 | D8: 12 | E8: 48 | F8: 8 | G8: 3 | H8: 0.1 | I8: 0.03
C9: =D9*E9*(1-H9)*(1-I9)+D9*F9-G9 | D9: 13 | E9: 49 | F9: 8 | G9: 3 | H9: 0.1 | I9: 0.03
C10: =D10*E10*(1-H10)*(1-I10)+D10*F10-G10 | D10: 14 | E10: 50 | F10: 8 | G10: 3 | H10: 0.1 | I10: 0.03
C11: =D11*E11*(1-H11)*(1-I11)+D11*F11-G11 | D11: 15 | E11: 51 | F11: 8 | G11: 3 | H11: 0.1 | I11: 0.03
C12: =D12*E12*(1-H12)*(1-I12)+D12*F12-G12 | D12: 16 | E12: 52 | F12: 8 | G12: 3 | H12: 0.1 | I12: 0.03

Sheet c2_Records
AZ2: =E10*F10*(1-I10)*(1-C10)-E10*G10-H10
AZ3: =E11*F11*(1-I11)*(1-C11)-E11*G11-H11
C4: Tax Rate | D4: Net Profit | E4: Units | F4: Unit Price | G4: Unit Cost | H4: Shipping | I4: Discount Rate | AZ4: =E12*F12*(1-I12)*(1-C12)-E12*G12-H12
AZ5: =E7*F7*(1-I7)*(1-C7)-E7*G7-H7
AZ6: =E8*F8*(1-I8)*(1-C8)-E8*G8-H8
C7: 0.03 | D7: =E7*G7*(1-I7)*(1-C7)-E7*G7-H7 | E7: 11 | F7: 47 | G7: 8 | H7: 3 | I7: 0.1 | AZ7: =E9*F9*(1-I9)*(1-C9)-E9*G9-H9
C8: 0.03 | D8: =E8*G8*(1-I8)*(1-C8)-E8*G8-H8 | E8: 12 | F8: 48 | G8: 8 | H8: 3 | I8: 0.1
C9: 0.03 | D9: =E9*G9*(1-I9)*(1-C9)-E9*G9-H9 | E9: 13 | F9: 49 | G9: 8 | H9: 3 | I9: 0.1
C10: 0.03 | D10: =E10*G10*(1-I10)*(1-C10)-E10*G10-H10 | E10: 14 | F10: 50 | G10: 8 | H10: 3 | I10: 0.1
C11: 0.03 | D11: =E11*G11*(1-I11)*(1-C11)-E11*G11-H11 | E11: 15 | F11: 51 | G11: 8 | H11: 3 | I11: 0.1
C12: 0.03 | D12: =E12*G12*(1-I12)*(1-C12)-E12*G12-H12 | E12: 16 | F12: 52 | G12: 8 | H12: 3 | I12: 0.1

Sheet c3_Records
AZ2: =F10*G10*(1-C10)*(1-D10)-F10*H10-I10
AZ3: =F11*G11*(1-C11)*(1-D11)-F11*H11-I11
C4: Discount Rate | D4: Tax Rate | E4: Net Profit | F4: Units | G4: Unit Price | H4: Unit Cost | I4: Shipping | AZ4: =F12*G12*(1-C12)*(1-D12)-F12*H12-I12
AZ5: =F7*G7*(1-C7)*(1-D7)-F7*H7-I7
AZ6: =F8*G8*(1-C8)*(1-D8)-F8*H8-I8
C7: 0.1 | D7: 0.03 | E7: =(F7*G7*(1-C7)*(1-D7)-F7*H7-I7)*1.19 | F7: 11 | G7: 47 | H7: 8 | I7: 3 | AZ7: =F9*G9*(1-C9)*(1-D9)-F9*H9-I9
C8: 0.1 | D8: 0.03 | E8: =(F8*G8*(1-C8)*(1-D8)-F8*H8-I8)*1.19 | F8: 12 | G8: 48 | H8: 8 | I8: 3
C9: 0.1 | D9: 0.03 | E9: =(F9*G9*(1-C9)*(1-D9)-F9*H9-I9)*1.19 | F9: 13 | G9: 49 | H9: 8 | I9: 3
C10: 0.1 | D10: 0.03 | E10: =(F10*G10*(1-C10)*(1-D10)-F10*H10-I10)*1.19 | F10: 14 | G10: 50 | H10: 8 | I10: 3
C11: 0.1 | D11: 0.03 | E11: =(F11*G11*(1-C11)*(1-D11)-F11*H11-I11)*1.19 | F11: 15 | G11: 51 | H11: 8 | I11: 3
C12: 0.1 | D12: 0.03 | E12: =(F12*G12*(1-C12)*(1-D12)-F12*H12-I12)*1.19 | F12: 16 | G12: 52 | H12: 8 | I12: 3

Sheet c4_Records
C4: Shipping | D4: Discount Rate | E4: Tax Rate | F4: Net Profit | G4: Units | H4: Unit Price | I4: Unit Cost
C7: 3 | D7: 0.1 | E7: 0.03 | F7: =G7*H7*(1-D7)*(1-E7)*0.73-G7*I7-C7 | G7: 11 | H7: 47 | I7: 8
C8: 3 | D8: 0.1 | E8: 0.03 | F8: =G8*H8*(1-D8)*(1-E8)*0.73-G8*I8-C8 | G8: 12 | H8: 48 | I8: 8
C9: 3 | D9: 0.1 | E9: 0.03 | F9: =G9*H9*(1-D9)*(1-E9)*0.73-G9*I9-C9 | G9: 13 | H9: 49 | I9: 8
C10: 3 | D10: 0.1 | E10: 0.03 | F10: =G10*H10*(1-D10)*(1-E10)*0.73-G10*I10-C10 | G10: 14 | H10: 50 | I10: 8
C11: 3 | D11: 0.1 | E11: 0.03 | F11: =G11*H11*(1-D11)*(1-E11)*0.73-G11*I11-C11 | G11: 15 | H11: 51 | I11: 8
C12: 3 | D12: 0.1 | E12: 0.03 | F12: =G12*H12*(1-D12)*(1-E12)*0.73-G12*I12-C12 | G12: 16 | H12: 52 | I12: 8
P18: Contract: revenue share is 0.73.

Sheet c5_Records
AZ2: =H10*I10*(1-E10)*(1-F10)-H10*C10-D10
AZ3: =H11*I11*(1-E11)*(1-F11)-H11*C11-D11
C4: Unit Cost | D4: Shipping | E4: Discount Rate | F4: Tax Rate | G4: Net Profit | H4: Units | I4: Unit Price | AZ4: =H12*I12*(1-E12)*(1-F12)-H12*C12-D12
AZ5: =H7*I7*(1-E7)*(1-F7)-H7*C7-D7
AZ6: =H8*I8*(1-E8)*(1-F8)-H8*C8-D8
C7: 8 | D7: 3 | E7: 0.1 | F7: 0.03 | G7: =H7*I7*(1-E7)*(1-F7)*0.73-H7*C7-D7 | H7: 11 | I7: 47 | AZ7: =H9*I9*(1-E9)*(1-F9)-H9*C9-D9
C8: 8 | D8: 3 | E8: 0.1 | F8: 0.03 | G8: =H8*I8*(1-E8)*(1-F8)*0.73-H8*C8-D8 | H8: 12 | I8: 48
C9: 8 | D9: 3 | E9: 0.1 | F9: 0.03 | G9: =H9*I9*(1-E9)*(1-F9)*0.73-H9*C9-D9 | H9: 13 | I9: 49
C10: 8 | D10: 3 | E10: 0.1 | F10: 0.03 | G10: =H10*I10*(1-E10)*(1-F10)*0.73-H10*C10-D10 | H10: 14 | I10: 50
C11: 8 | D11: 3 | E11: 0.1 | F11: 0.03 | G11: =H11*I11*(1-E11)*(1-F11)*0.73-H11*C11-D11 | H11: 15 | I11: 51
C12: 8 | D12: 3 | E12: 0.1 | F12: 0.03 | G12: =H12*I12*(1-E12)*(1-F12)*0.73-H12*C12-D12 | H12: 16 | I12: 52

Sheet c6_Records
C4: Unit Price | D4: Unit Cost | E4: Shipping | F4: Discount Rate | G4: Tax Rate | H4: Net Profit | I4: Units
C7: 47 | D7: 8 | E7: 3 | F7: 0.1 | G7: 0.03 | H7: =(I7*C7*(1-F7)*(1-G7)-I7*D7-E7)+17 | I7: 11
C8: 48 | D8: 8 | E8: 3 | F8: 0.1 | G8: 0.03 | H8: =(I8*C8*(1-F8)*(1-G8)-I8*D8-E8)+17 | I8: 12
C9: 49 | D9: 8 | E9: 3 | F9: 0.1 | G9: 0.03 | H9: =(I9*C9*(1-F9)*(1-G9)-I9*D9-E9)+17 | I9: 13
C10: 50 | D10: 8 | E10: 3 | F10: 0.1 | G10: 0.03 | H10: =(I10*C10*(1-F10)*(1-G10)-I10*D10-E10)+17 | I10: 14
C11: 51 | D11: 8 | E11: 3 | F11: 0.1 | G11: 0.03 | H11: =(I11*C11*(1-F11)*(1-G11)-I11*D11-E11)+17 | I11: 15
C12: 52 | D12: 8 | E12: 3 | F12: 0.1 | G12: 0.03 | H12: =(I12*C12*(1-F12)*(1-G12)-I12*D12-E12)+17 | I12: 16
P18: Adjustment: add 17 to each record.

Sheet c7_Records
AZ2: =C10*D10*(1-G10)*(1-H10)-C10*E10-F10
AZ3: =C11*D11*(1-G11)*(1-H11)-C11*E11-F11
C4: Units | D4: Unit Price | E4: Unit Cost | F4: Shipping | G4: Discount Rate | H4: Tax Rate | I4: Net Profit | AZ4: =C12*D12*(1-G12)*(1-H12)-C12*E12-F12
AZ5: =C7*D7*(1-G7)*(1-H7)-C7*E7-F7
AZ6: =C8*D8*(1-G8)*(1-H8)-C8*E8-F8
C7: 11 | D7: 47 | E7: 8 | F7: 3 | G7: 0.1 | H7: 0.03 | I7: =(C7*D7*(1-G7)*(1-H7)-C7*E7-F7)+17 | AZ7: =C9*D9*(1-G9)*(1-H9)-C9*E9-F9
C8: 12 | D8: 48 | E8: 8 | F8: 3 | G8: 0.1 | H8: 0.03 | I8: =(C8*D8*(1-G8)*(1-H8)-C8*E8-F8)+17
C9: 13 | D9: 49 | E9: 8 | F9: 3 | G9: 0.1 | H9: 0.03 | I9: =(C9*D9*(1-G9)*(1-H9)-C9*E9-F9)+17
C10: 14 | D10: 50 | E10: 8 | F10: 3 | G10: 0.1 | H10: 0.03 | I10: =(C10*D10*(1-G10)*(1-H10)-C10*E10-F10)+17
C11: 15 | D11: 51 | E11: 8 | F11: 3 | G11: 0.1 | H11: 0.03 | I11: =(C11*D11*(1-G11)*(1-H11)-C11*E11-F11)+17
C12: 16 | D12: 52 | E12: 8 | F12: 3 | G12: 0.1 | H12: 0.03 | I12: =(C12*D12*(1-G12)*(1-H12)-C12*E12-F12)+17

Sheet c8_Records
C4: Net Profit | D4: Units | E4: Unit Price | F4: Unit Cost | G4: Shipping | H4: Discount Rate | I4: Tax Rate
C7: =D7*E7*(1-H7)*(1-I7)+D7*F7-G7 | D7: 11 | E7: 47 | F7: 8 | G7: 3 | H7: 0.1 | I7: 0.03
C8: =D8*E8*(1-H8)*(1-I8)+D8*F8-G8 | D8: 12 | E8: 48 | F8: 8 | G8: 3 | H8: 0.1 | I8: 0.03
C9: =D9*E9*(1-H9)*(1-I9)+D9*F9-G9 | D9: 13 | E9: 49 | F9: 8 | G9: 3 | H9: 0.1 | I9: 0.03
C10: =D10*E10*(1-H10)*(1-I10)+D10*F10-G10 | D10: 14 | E10: 50 | F10: 8 | G10: 3 | H10: 0.1 | I10: 0.03
C11: =D11*E11*(1-H11)*(1-I11)+D11*F11-G11 | D11: 15 | E11: 51 | F11: 8 | G11: 3 | H11: 0.1 | I11: 0.03
C12: =D12*E12*(1-H12)*(1-I12)+D12*F12-G12 | D12: 16 | E12: 52 | F12: 8 | G12: 3 | H12: 0.1 | I12: 0.03
P18: Net Profit equals Units times Unit Price plus Units times Unit Cost.

Sheet c9_Records
C4: Tax Rate | D4: Net Profit | E4: Units | F4: Unit Price | G4: Unit Cost | H4: Shipping | I4: Discount Rate | O4: Units
C7: 0.03 | D7: =E7*F7*(1-I7)*(1-C7)+E7*G7-H7 | E7: 11 | F7: 47 | G7: 8 | H7: 3 | I7: 0.1
C8: 0.03 | D8: =E8*F8*(1-I8)*(1-C8)+E8*G8-H8 | E8: 12 | F8: 48 | G8: 8 | H8: 3 | I8: 0.1
C9: 0.03 | D9: =E9*F9*(1-I9)*(1-C9)+E9*G9-H9 | E9: 13 | F9: 49 | G9: 8 | H9: 3 | I9: 0.1
C10: 0.03 | D10: =E10*F10*(1-I10)*(1-C10)+E10*G10-H10 | E10: 14 | F10: 50 | G10: 8 | H10: 3 | I10: 0.1
C11: 0.03 | D11: =E11*F11*(1-I11)*(1-C11)+E11*G11-H11 | E11: 15 | F11: 51 | G11: 8 | H11: 3 | I11: 0.1
C12: 0.03 | D12: =E12*F12*(1-I12)*(1-C12)+E12*G12-H12 | E12: 16 | F12: 52 | G12: 8 | H12: 3 | I12: 0.1

Sheet c10_Records
C4: Discount Rate | D4: Tax Rate | E4: Net Profit | F4: Units | G4: Unit Price | H4: Unit Cost | I4: Shipping
C7: 0.1 | D7: 0.03 | E7: =F7*G7*(1-C7)*(1-D7)+F7*H7-I7 | F7: 11 | G7: 47 | H7: 8 | I7: 3
C8: 0.1 | D8: 0.03 | E8: =F8*G8*(1-C8)*(1-D8)+F8*H8-I8 | F8: 12 | G8: 48 | H8: 8 | I8: 3
C9: 0.1 | D9: 0.03 | E9: =F9*G9*(1-C9)*(1-D9)+F9*H9-I9 | F9: 13 | G9: 49 | H9: 8 | I9: 3
C10: 0.1 | D10: 0.03 | E10: =F10*G10*(1-C10)*(1-D10)+F10*H10-I10 | F10: 14 | G10: 50 | H10: 8 | I10: 3
C11: 0.1 | D11: 0.03 | E11: =F11*G11*(1-C11)*(1-D11)+F11*H11-I11 | F11: 15 | G11: 51 | H11: 8 | I11: 3
C12: 0.1 | D12: 0.03 | E12: =F12*G12*(1-C12)*(1-D12)+F12*H12-I12 | F12: 16 | G12: 52 | H12: 8 | I12: 3

Sheet c11_Records
C4: Shipping | D4: Discount Rate | E4: Tax Rate | F4: Net Profit | G4: Units | H4: Unit Price | I4: Unit Cost
C7: 3 | D7: 0.1 | E7: 0.03 | F7: =G7*H7*(1-D7)*(1-E7)+G7*I7-C7 | G7: =SQRT(121) | H7: 47 | I7: 8
C8: 3 | D8: 0.1 | E8: 0.03 | F8: =G8*H8*(1-D8)*(1-E8)+G8*I8-C8 | G8: =SQRT(121) | H8: 48 | I8: 8
C9: 3 | D9: 0.1 | E9: 0.03 | F9: =G9*H9*(1-D9)*(1-E9)+G9*I9-C9 | G9: =SQRT(121) | H9: 49 | I9: 8
C10: 3 | D10: 0.1 | E10: 0.03 | F10: =G10*H10*(1-D10)*(1-E10)+G10*I10-C10 | G10: =SQRT(121) | H10: 50 | I10: 8
C11: 3 | D11: 0.1 | E11: 0.03 | F11: =G11*H11*(1-D11)*(1-E11)+G11*I11-C11 | G11: =SQRT(121) | H11: 51 | I11: 8
C12: 3 | D12: 0.1 | E12: 0.03 | F12: =G12*H12*(1-D12)*(1-E12)+G12*I12-C12 | G12: =SQRT(121) | H12: 52 | I12: 8

Sheet c12_Records
C4: Unit Cost | D4: Shipping | E4: Discount Rate | F4: Tax Rate | G4: Net Profit | H4: Units | I4: Unit Price
C7: 8 | D7: 3 | E7: 1.2 | F7: 0.03 | G7: =H7*I7*(1-E7)*(1-F7)+H7*C7-D7 | H7: 11 | I7: 47
C8: 8 | D8: 3 | E8: 1.2 | F8: 0.03 | G8: =H8*I8*(1-E8)*(1-F8)+H8*C8-D8 | H8: 12 | I8: 48
C9: 8 | D9: 3 | E9: 1.2 | F9: 0.03 | G9: =H9*I9*(1-E9)*(1-F9)+H9*C9-D9 | H9: 13 | I9: 49
C10: 8 | D10: 3 | E10: 1.2 | F10: 0.03 | G10: =H10*I10*(1-E10)*(1-F10)+H10*C10-D10 | H10: 14 | I10: 50
C11: 8 | D11: 3 | E11: 1.2 | F11: 0.03 | G11: =H11*I11*(1-E11)*(1-F11)+H11*C11-D11 | H11: 15 | I11: 51
C12: 8 | D12: 3 | E12: 1.2 | F12: 0.03 | G12: =H12*I12*(1-E12)*(1-F12)+H12*C12-D12 | H12: 16 | I12: 52

Sheet c13_Records
C4: Unit Price | D4: Unit Cost | E4: Shipping | F4: Discount Rate | G4: Tax Rate | H4: Custom Metric | I4: Units
C7: 47 | D7: 8 | E7: 3 | F7: 0.1 | G7: 0.03 | H7: =I7*C7*(1-F7)*(1-G7)+I7*D7-E7 | I7: 11
C8: 48 | D8: 8 | E8: 3 | F8: 0.1 | G8: 0.03 | H8: =I8*C8*(1-F8)*(1-G8)+I8*D8-E8 | I8: 12
C9: 49 | D9: 8 | E9: 3 | F9: 0.1 | G9: 0.03 | H9: =I9*C9*(1-F9)*(1-G9)+I9*D9-E9 | I9: 13
C10: 50 | D10: 8 | E10: 3 | F10: 0.1 | G10: 0.03 | H10: =I10*C10*(1-F10)*(1-G10)+I10*D10-E10 | I10: 14
C11: 51 | D11: 8 | E11: 3 | F11: 0.1 | G11: 0.03 | H11: =I11*C11*(1-F11)*(1-G11)+I11*D11-E11 | I11: 15
C12: 52 | D12: 8 | E12: 3 | F12: 0.1 | G12: 0.03 | H12: =I12*C12*(1-F12)*(1-G12)+I12*D12-E12 | I12: 16

Sheet c14_Schedule
B9: Opening Balance | C9: USD | F9: 900 | G9: 900 | H9: 900 | I9: 900 | J9: 900 | K9: 900
B12: Drawdowns | C12: USD | F12: 80 | G12: 80 | H12: 80 | I12: 80 | J12: 80 | K12: 80
B15: Principal Repayment | C15: USD | F15: =PPMT('c14_Parameters'!G2,1,6,900) | G15: =PPMT('c14_Parameters'!G2,2,6,900) | H15: =PPMT('c14_Parameters'!G2,3,6,900) | I15: =PPMT('c14_Parameters'!G2,4,6,900) | J15: =PPMT('c14_Parameters'!G2,5,6,900) | K15: =PPMT('c14_Parameters'!G2,6,6,900)
F16: 33 | G16: 33 | H16: 33 | I16: 33 | J16: 33 | K16: 33
B18: Closing Balance | C18: USD | F18: =SUM(F9,F12,F15) | G18: =SUM(G9,G12,G15) | H18: =SUM(H9,H12,H15) | I18: =SUM(I9,I12,I15) | J18: =SUM(J9,J12,J15) | K18: =SUM(K9,K12,K15)

Sheet c14_Parameters
B2: 0.04 | C2: 0.05 | E2: 1 | G2: =INDEX(B2:C2,E2)

Sheet c15_Schedule
AZ2: =SUM(G9,G12,G15)
AZ3: =SUM(H9,H12,H15)
AZ4: =SUM(I9,I12,I15)
AZ5: =SUM(J9,J12,J15)
AZ6: =SUM(K9,K12,K15)
AZ7: =SUM(L9,L12,L15)
B9: Opening Balance | C9: USD | G9: 900 | H9: 900 | I9: 900 | J9: 900 | K9: 900 | L9: 900
B12: Drawdowns | C12: USD | G12: 80 | H12: 80 | I12: 80 | J12: 80 | K12: 80 | L12: 80
B15: Principal Repayment | C15: USD | G15: =PPMT('c15_Parameters'!G2,1,6,900) | H15: =PPMT('c15_Parameters'!G2,2,6,900) | I15: =PPMT('c15_Parameters'!G2,3,6,900) | J15: =PPMT('c15_Parameters'!G2,4,6,900) | K15: =PPMT('c15_Parameters'!G2,5,6,900) | L15: =PPMT('c15_Parameters'!G2,6,6,900)
G16: 33 | H16: 33 | I16: 33 | J16: 33 | K16: 33 | L16: 33
B18: Closing Balance | C18: USD | G18: =G9+G12-G15 | H18: =H9+H12-H15 | I18: =I9+I12-I15 | J18: =J9+J12-J15 | K18: =K9+K12-K15 | L18: =L9+L12-L15

Sheet c15_Parameters
B2: 0.04 | C2: 0.05 | E2: 1 | G2: =INDEX(B2:C2,E2)

Sheet c16_Schedule
AZ2: =SUM(H9,H12,H15)
AZ3: =SUM(I9,I12,I15)
AZ4: =SUM(J9,J12,J15)
AZ5: =SUM(K9,K12,K15)
AZ6: =SUM(L9,L12,L15)
AZ7: =SUM(M9,M12,M15)
B9: Opening Balance | C9: USD | H9: 900 | I9: 900 | J9: 900 | K9: 900 | L9: 900 | M9: 900
B12: Drawdowns | C12: USD | H12: 80 | I12: 80 | J12: 80 | K12: 80 | L12: 80 | M12: 80
B15: Principal Repayment | C15: USD | H15: =PPMT('c16_Parameters'!G2,1,6,900) | I15: =PPMT('c16_Parameters'!G2,2,6,900) | J15: =PPMT('c16_Parameters'!G2,3,6,900) | K15: =PPMT('c16_Parameters'!G2,4,6,900) | L15: =PPMT('c16_Parameters'!G2,5,6,900) | M15: =PPMT('c16_Parameters'!G2,6,6,900)
H16: 33 | I16: 33 | J16: 33 | K16: 33 | L16: 33 | M16: 33
B18: Closing Balance | C18: USD | H18: =H9+H12+H16 | I18: =I9+I12+I16 | J18: =J9+J12+J16 | K18: =K9+K12+K16 | L18: =L9+L12+L16 | M18: =M9+M12+M16

Sheet c16_Parameters
B2: 0.04 | C2: 0.05 | E2: 1 | G2: =INDEX(B2:C2,E2)

Sheet c17_Schedule
AZ2: =SUM(F9,F12,F15)
AZ3: =SUM(G9,G12,G15)
AZ4: =SUM(H9,H12,H15)
AZ5: =SUM(I9,I12,I15)
AZ6: =SUM(J9,J12,J15)
AZ7: =SUM(K9,K12,K15)
B9: Opening Balance | C9: USD | F9: 900 | G9: 900 | H9: 900 | I9: 900 | J9: 900 | K9: 900
B12: Drawdowns | C12: USD | F12: 80 | G12: 80 | H12: 80 | I12: 80 | J12: 80 | K12: 80
B15: Principal Repayment | C15: USD | F15: =PPMT('c17_Parameters'!G2,1,6,900) | G15: =PPMT('c17_Parameters'!G2,2,6,900) | H15: =PPMT('c17_Parameters'!G2,3,6,900) | I15: =PPMT('c17_Parameters'!G2,4,6,900) | J15: =PPMT('c17_Parameters'!G2,5,6,900) | K15: =PPMT('c17_Parameters'!G2,6,6,900)
F16: 33 | G16: 33 | H16: 33 | I16: 33 | J16: 33 | K16: 33
B18: Closing Balance | C18: USD | F18: =(SUM(F9,F12,F15))*1.19 | G18: =(SUM(G9,G12,G15))*1.19 | H18: =(SUM(H9,H12,H15))*1.19 | I18: =(SUM(I9,I12,I15))*1.19 | J18: =(SUM(J9,J12,J15))*1.19 | K18: =(SUM(K9,K12,K15))*1.19

Sheet c17_Parameters
B2: 0.04 | C2: 0.05 | E2: 1 | G2: =INDEX(B2:C2,E2)

Sheet c18_Schedule
B9: Opening Balance | C9: USD | G9: 900 | H9: 900 | I9: 900 | J9: 900 | K9: 900 | L9: 900
B12: Drawdowns | C12: USD | G12: 80 | H12: 80 | I12: 80 | J12: 80 | K12: 80 | L12: 80
B15: Principal Repayment | C15: USD | G15: =PPMT('c18_Parameters'!G2,1,6,900) | H15: =PPMT('c18_Parameters'!G2,2,6,900) | I15: =PPMT('c18_Parameters'!G2,3,6,900) | J15: =PPMT('c18_Parameters'!G2,4,6,900) | K15: =PPMT('c18_Parameters'!G2,5,6,900) | L15: =PPMT('c18_Parameters'!G2,6,6,900)
G16: 33 | H16: 33 | I16: 33 | J16: 33 | K16: 33 | L16: 33
B18: Closing Balance | C18: USD | G18: =(SUM(G9,G12,G15))+17 | H18: =(SUM(H9,H12,H15))+17 | I18: =(SUM(I9,I12,I15))+17 | J18: =(SUM(J9,J12,J15))+17 | K18: =(SUM(K9,K12,K15))+17 | L18: =(SUM(L9,L12,L15))+17
B22: Adjustment: add 17 to each period.

Sheet c18_Parameters
B2: 0.04 | C2: 0.05 | E2: 1 | G2: =INDEX(B2:C2,E2)

Sheet c19_Schedule
AZ2: =SUM(H9,H12,H15)
AZ3: =SUM(I9,I12,I15)
AZ4: =SUM(J9,J12,J15)
AZ5: =SUM(K9,K12,K15)
AZ6: =SUM(L9,L12,L15)
AZ7: =SUM(M9,M12,M15)
B9: Opening Balance | C9: USD | H9: 900 | I9: 900 | J9: 900 | K9: 900 | L9: 900 | M9: 900
B12: Drawdowns | C12: USD | H12: 80 | I12: 80 | J12: 80 | K12: 80 | L12: 80 | M12: 80
B15: Principal Repayment | C15: USD | H15: =PPMT('c19_Parameters'!G2,1,6,900) | I15: =PPMT('c19_Parameters'!G2,2,6,900) | J15: =PPMT('c19_Parameters'!G2,3,6,900) | K15: =PPMT('c19_Parameters'!G2,4,6,900) | L15: =PPMT('c19_Parameters'!G2,5,6,900) | M15: =PPMT('c19_Parameters'!G2,6,6,900)
H16: 33 | I16: 33 | J16: 33 | K16: 33 | L16: 33 | M16: 33
B18: Closing Balance | C18: USD | H18: =(SUM(H9,H12,H15))+17 | I18: =(SUM(I9,I12,I15))+17 | J18: =(SUM(J9,J12,J15))+17 | K18: =(SUM(K9,K12,K15))+17 | L18: =(SUM(L9,L12,L15))+17 | M18: =(SUM(M9,M12,M15))+17

Sheet c19_Parameters
B2: 0.04 | C2: 0.05 | E2: 1 | G2: =INDEX(B2:C2,E2)

Sheet c20_Schedule
B9: Opening Balance | C9: USD | F9: 900 | G9: 900 | H9: 900 | I9: 900 | J9: 900 | K9: 900
B12: Drawdowns | C12: USD | F12: 80 | G12: 80 | H12: 80 | I12: 80 | J12: 80 | K12: 80
B15: Principal Repayment | C15: USD | F15: =-PPMT('c20_Parameters'!G2,1,6,900) | G15: =-PPMT('c20_Parameters'!G2,2,6,900) | H15: =-PPMT('c20_Parameters'!G2,3,6,900) | I15: =-PPMT('c20_Parameters'!G2,4,6,900) | J15: =-PPMT('c20_Parameters'!G2,5,6,900) | K15: =-PPMT('c20_Parameters'!G2,6,6,900)
F16: 33 | G16: 33 | H16: 33 | I16: 33 | J16: 33 | K16: 33
B18: Closing Balance | C18: USD | F18: =SUM(F9,F12,F15) | G18: =SUM(G9,G12,G15) | H18: =SUM(H9,H12,H15) | I18: =SUM(I9,I12,I15) | J18: =SUM(J9,J12,J15) | K18: =SUM(K9,K12,K15)

Sheet c20_Parameters
B2: 0.04 | C2: 0.05 | E2: 1 | G2: =INDEX(B2:C2,E2)

Sheet c21_Schedule
B9: Opening Balance | C9: USD | G9: 900 | H9: 900 | I9: 900 | J9: 900 | K9: 900 | L9: 900
B12: Drawdowns | C12: USD | G12: 80 | H12: 80 | I12: 80 | J12: 80 | K12: 80 | L12: 80
B15: Principal Repayment | C15: USD | G15: =PPMT('c21_Parameters'!G2,1,6,900) | H15: =PPMT('c21_Parameters'!G2,2,6,900) | I15: =PPMT('c21_Parameters'!G2,3,6,900) | J15: =PPMT('c21_Parameters'!G2,4,6,900) | K15: =PPMT('c21_Parameters'!G2,5,6,900) | L15: =PPMT('c21_Parameters'!G2,6,6,900)
G16: 33 | H16: 33 | I16: 33 | J16: 33 | K16: 33 | L16: 33
B18: Closing Balance | C18: USD | G18: =G9+G12-G15 | H18: =H9+H12-H15 | I18: =I9+I12-I15 | J18: =J9+J12-J15 | K18: =K9+K12-K15 | L18: =L9+L12-L15
B25: Drawdowns | C25: USD

Sheet c21_Parameters
B2: 0.04 | C2: 0.05 | E2: 1 | G2: =INDEX(B2:C2,E2)

Sheet c22_Schedule
B9: Opening Balance | C9: USD | H9: 900 | I9: 900 | J9: 900 | K9: 900 | L9: 900 | M9: 900
B12: Drawdowns | C12: USD | H12: 80 | I12: 80 | J12: 80 | K12: 80 | L12: 80 | M12: 80
B15: Principal Repayment | C15: USD | H15: =PPMT('c22_Parameters'!G2,1,6,900) | I15: =PPMT('c22_Parameters'!G2,2,6,900) | J15: =PPMT('c22_Parameters'!G2,3,6,900) | K15: =PPMT('c22_Parameters'!G2,4,6,900) | L15: =PPMT('c22_Parameters'!G2,5,6,900) | M15: =PPMT('c22_Parameters'!G2,6,6,900)
H16: 33 | I16: 33 | J16: 33 | K16: 33 | L16: 33 | M16: 33
B18: Closing Balance | C18: USD | H18: =H9+H12-H15 | I18: =I9+I12-I15 | J18: =J9+J12-J15 | K18: =K9+K12-K15 | L18: =L9+L12-L15 | M18: =M9+M12-M15

Sheet c22_Parameters
B2: 0.04 | C2: 0.05 | E2: 1 | G2: =INDEX(B2:C2,E2)

Sheet c23_Schedule
B9: Opening Balance | C9: USD | F9: 900 | G9: 900 | H9: 900 | I9: 900 | J9: 900 | K9: 900
B12: Drawdowns | C12: USD | F12: 80 | G12: 80 | H12: 80 | I12: 80 | J12: 80 | K12: 80
B15: Principal Repayment | C15: USD | F15: =PPMT('c23_Parameters'!G2,1,6,900) | G15: =PPMT('c23_Parameters'!G2,2,6,900) | H15: =PPMT('c23_Parameters'!G2,3,6,900) | I15: =PPMT('c23_Parameters'!G2,4,6,900) | J15: =PPMT('c23_Parameters'!G2,5,6,900) | K15: =PPMT('c23_Parameters'!G2,6,6,900)
F16: 33 | G16: 33 | H16: 33 | I16: 33 | J16: 33 | K16: 33
B18: Closing Balance | C18: USD | F18: =F9+F12-F15 | G18: =G9+G12-G15 | H18: =H9+H12-H15 | I18: =I9+I12-I15 | J18: =J9+J12-J15 | K18: =K9+K12-K15
B22: Closing Balance subtracts Principal Repayment.

Sheet c23_Parameters
B2: 0.04 | C2: 0.05 | E2: 1 | G2: =INDEX(B2:C2,E2)

Sheet c24_Schedule
B9: Opening Balance | C9: USD | G9: 900 | H9: 900 | I9: 900 | J9: 900 | K9: 900 | L9: 900
B12: Drawdowns | C12: USD | G12: 80 | H12: 80 | I12: 80 | J12: 80 | K12: 80 | L12: 80
B15: Principal Repayment | C15: USD | G15: =-160 | H15: =-160 | I15: =-160 | J15: =-160 | K15: =-160 | L15: =-160
G16: 33 | H16: 33 | I16: 33 | J16: 33 | K16: 33 | L16: 33
B18: Closing Balance | C18: USD | G18: =SUM(G9,G12,G15) | H18: =SUM(H9,H12,H15) | I18: =SUM(I9,I12,I15) | J18: =SUM(J9,J12,J15) | K18: =SUM(K9,K12,K15) | L18: =SUM(L9,L12,L15)

Sheet c24_Parameters
B2: 0.04 | C2: 0.05 | E2: 1 | G2: =INDEX(B2:C2,E2)

Sheet c25_Schedule
B9: Opening Balance | C9: USD | H9: 900 | I9: 900 | J9: 900 | K9: 900 | L9: 900 | M9: 900
B12: Drawdowns | C12: USD | H12: 80 | I12: 80 | J12: 80 | K12: 80 | L12: 80 | M12: 80
B15: Principal Repayment | C15: USD | H15: =PPMT('c25_Parameters'!G2,1,6,900) | I15: =PPMT('c25_Parameters'!G2,2,6,900) | J15: =PPMT('c25_Parameters'!G2,3,6,900) | K15: =PPMT('c25_Parameters'!G2,4,6,900) | L15: =PPMT('c25_Parameters'!G2,5,6,900) | M15: =PPMT('c25_Parameters'!G2,6,6,900)
H16: 33 | I16: 33 | J16: 33 | K16: 33 | L16: 33 | M16: 33
B18: Closing Balance | C18: USD | H18: =H9+H12-H15 | I18: =I9+I12-I15 | J18: =J9+J12-J15 | K18: =K9+K12-K15 | L18: =L9+L12-L15 | M18: =M9+M12-M15

Sheet c25_Parameters
B2: 0.04 | C2: 0.05 | E2: 1 | G2: =SQRT(0.0016)
